recsyslearn/__init__.py
recsyslearn/utils.py
recsyslearn/accuracy/__init__.py
recsyslearn/accuracy/metrics.py
recsyslearn/beyond_accuracy/__init__.py
recsyslearn/beyond_accuracy/metrics.py
recsyslearn/dataset/__init__.py
recsyslearn/dataset/segmentations.py
recsyslearn/dataset/utils.py
recsyslearn/errors/__init__.py
recsyslearn/errors/errors.py
recsyslearn/fairness/__init__.py
recsyslearn/fairness/metrics.py
recsyslearn/fairness/utils.py
recsyslearn-2.0.2.dist-info/LICENSE
recsyslearn-2.0.2.dist-info/METADATA
recsyslearn-2.0.2.dist-info/WHEEL
recsyslearn-2.0.2.dist-info/top_level.txt
recsyslearn-2.0.2.dist-info/RECORD
