Metadata-Version: 2.1
Name: recsyslearn
Version: 2.0.2
Summary: A library to compute fairness of recommender systems.
Home-page: https://github.com/giuliowaitforitdavide/recsyslearn
Author: Giulio Davide Carparelli
Author-email: giulio.davide.97@gmail.com
License: GNU General Public License v3
Keywords: recsyslearn
Classifier: License :: OSI Approved :: GNU General Public License v3 (GPLv3)
Classifier: Topic :: Scientific/Engineering :: Artificial Intelligence
Classifier: Topic :: Scientific/Engineering :: Mathematics
Classifier: Topic :: Software Development :: Libraries :: Python Modules
Classifier: Programming Language :: Python :: 3.10
Requires-Python: >=3.10
License-File: LICENSE
Requires-Dist: numpy
Requires-Dist: pandas
